Workbook

Sheet category analysis
A1: Category | B1: Sum of Sales
A2: Beauty | B2: 348142.5
A3: Electronics | B3: 666129.5
A4: Fashion | B4: 493551.5
A5: Home & Kitchen | B5: 794730.5
A6: Grand Total | B6: 2302554

Sheet Regional_Analysis
A3: Region | B3: Sum of Sales
A4: East | B4: 337615
A5: North | B5: 549519
A6: South | B6: 778244
A7: West | B7: 637176
A8: Grand Total | B8: 2302554

Sheet Product_Analysis
A3: Product | B3: Sum of Profit
A4: Air Fryer | B4: 91731.67
A5: Coffee Maker | B5: 71130.57
A6: Smart Watch | B6: 67763.29
A7: Sneakers | B7: 57020.63
A8: Wireless Earbuds | B8: 65109.78
A9: Grand Total | B9: 352755.94

Sheet Monthly_Analysis
A3: Month | B3: Sum of Sales
A4: 45658 | B4: 137766
A5: 45689 | B5: 105568
A6: 45717 | B6: 133660
A7: 45748 | B7: 153271
A8: 45778 | B8: 67031.5
A9: 45809 | B9: 112395.5
A10: 45839 | B10: 109816.5
A11: 45870 | B11: 143219
A12: 45901 | B12: 118736.5
A13: 45931 | B13: 125577.5
A14: 45962 | B14: 91974.5
A15: 45992 | B15: 90425.5
... A23: 46235 | B23: 55468
A24: Grand Total | B24: 2302554

Sheet Dashboard
A1: E-COMMERCE BUSINESS ANALYTICS DASHBOARD
A2: Revenue • Profitability • Customers • Regional & Product Performance
A4: TOTAL REVENUE | C4: TOTAL PROFIT | E4: TOTAL ORDERS | G4: AVG ORDER VALUE | J4: PROFIT MARGIN | L4: UNIQUE CUSTOMERS
A5: =Analysis!B4 -> 2302554 | C5: =Analysis!B6 -> 758699.98 | E5: =Analysis!B7 -> 500 | G5: =Analysis!B9 -> 4605.108 | J5: =Analysis!B10 -> 0.32950366 | L5: =Analysis!B11 -> 263
A40: BUSINESS INSIGHTS & RECOMMENDATIONS
A42: 1. Revenue Performance
A43: Monthly revenue trends help identify growth patterns and periods of stronger or weaker sales.
A45: 2. Category Performance
A46: Compare revenue and profit margins across Electronics, Fashion, Beauty, and Home & Kitchen to identify the strongest business categories.
A48: 3. Product Performance
A49: Top-profit products should receive priority in inventory planning and marketing campaigns.
A51: 4. Regional Performance
A52: Regional revenue differences can help identify locations with higher growth potential
A54: 5. Customer Value
A55: Top customers contribute a significant share of revenue and should be targeted through retention strategies and personalized offers
A57: 1. Focus on high-profit products
... A73: s

Sheet Customer_Analysis
A3: Customer_ID | B3: Sum of Sales
A4: CUST1137 | B4: 42439
A5: CUST1275 | B5: 32616.5
A6: CUST1019 | B6: 28570
A7: CUST1181 | B7: 26569.5
A8: CUST1047 | B8: 24973
A9: CUST1222 | B9: 24931
A10: CUST1243 | B10: 24772
A11: CUST1333 | B11: 24330
A12: CUST1281 | B12: 23869
A13: CUST1240 | B13: 22012
A14: Grand Total | B14: 275082

Sheet Payment_Analysis
A3: Payment_method | B3: Sum of Sales
A4: Cash on Delivery | B4: 377603.5
A5: Credit Card | B5: 542717
A6: Debit Card | B6: 418543
A7: Net Banking | B7: 164937
A8: UPI | B8: 798753.5
A9: Grand Total | B9: 2302554

Sheet Profitability_Analysis
A3: Category | B3: Sum of Sales | C3: Sum of Profit | D3: Profit Margin
A4: Beauty | B4: 348142.5 | C4: 126138.3 | D4: =C4/B4 -> 0.36231802
A5: Electronics | B5: 666129.5 | C5: 216314.92 | D5: =C5/B5 -> 0.32473403
A6: Fashion | B6: 493551.5 | C6: 172755.37 | D6: =C6/B6 -> 0.35002501
A7: Home & Kitchen | B7: 794730.5 | C7: 243491.39 | D7: =C7/B7 -> 0.30638234
A8: Grand Total | B8: 2302554 | C8: 758699.98

Sheet raw-data
A1: Order_ID | B1: Order_Date | C1: Month | D1: Customer_ID | E1: Product | F1: Category | G1: Region | H1: Quantity | I1: Unit_Price | J1: Discount | K1: Sales | L1: Cost | M1: Profit | N1: Payment_method
A2: ORD10051 | B2: 45658 | C2: =DATE(YEAR(B2),MONTH(B2),1) -> 45658 | D2: CUST1117 | E2: Perfume | F2: Beauty | G2: North | H2: 1 | I2: 3380 | J2: 0.1 | K2: 3042 | L2: 2103.57 | M2: 938.43 | N2: UPI
A3: ORD10162 | B3: 45658 | C3: =DATE(YEAR(B3),MONTH(B3),1) -> 45658 | D3: CUST1192 | E3: Wireless Earbuds | F3: Electronics | G3: South | H3: 1 | I3: 2420 | J3: 0.1 | K3: 2178 | L3: 1564.68 | M3: 613.32 | N3: Debit Card
A4: ORD10119 | B4: 45660 | C4: =DATE(YEAR(B4),MONTH(B4),1) -> 45658 | D4: CUST1073 | E4: Backpack | F4: Fashion | G4: West | H4: 3 | I4: 1610 | J4: 0.15 | K4: 4105.5 | L4: 2663.92 | M4: 1441.58 | N4: UPI
A5: ORD10011 | B5: 45662 | C5: =DATE(YEAR(B5),MONTH(B5),1) -> 45658 | D5: CUST1179 | E5: Smart Watch | F5: Electronics | G5: West | H5: 2 | I5: 3980 | J5: 0.1 | K5: 7164 | L5: 4857.63 | M5: 2306.37 | N5: Debit Card
A6: ORD10305 | B6: 45662 | C6: =DATE(YEAR(B6),MONTH(B6),1) -> 45658 | D6: CUST1224 | E6: Backpack | F6: Fashion | G6: West | H6: 1 | I6: 1570 | J6: 0.1 | K6: 1413 | L6: 914.1 | M6: 498.9 | N6: UPI
A7: ORD10070 | B7: 45664 | C7: =DATE(YEAR(B7),MONTH(B7),1) -> 45658 | D7: CUST1015 | E7: Bluetooth Speaker | F7: Electronics | G7: North | H7: 3 | I7: 2060 | J7: 0 | K7: 6180 | L7: 3568.5 | M7: 2611.5 | N7: Cash on Delivery
A8: ORD10100 | B8: 45664 | C8: =DATE(YEAR(B8),MONTH(B8),1) -> 45658 | D8: CUST1082 | E8: Coffee Maker | F8: Home & Kitchen | G8: North | H8: 3 | I8: 3600 | J8: 0 | K8: 10800 | L8: 6656.6 | M8: 4143.4 | N8: Debit Card
A9: ORD10146 | B9: 45664 | C9: =DATE(YEAR(B9),MONTH(B9),1) -> 45658 | D9: CUST1188 | E9: Hoodie | F9: Fashion | G9: North | H9: 2 | I9: 2000 | J9: 0.15 | K9: 3400 | L9: 2236.62 | M9: 1163.38 | N9: Credit Card
A10: ORD10186 | B10: 45664 | C10: =DATE(YEAR(B10),MONTH(B10),1) -> 45658 | D10: CUST1276 | E10: Hoodie | F10: Fashion | G10: South | H10: 1 | I10: 2030 | J10: 0 | K10: 2030 | L10: 1139.38 | M10: 890.62 | N10: UPI
A11: ORD10022 | B11: 45666 | C11: =DATE(YEAR(B11),MONTH(B11),1) -> 45658 | D11: CUST1116 | E11: Casual Shirt | F11: Fashion | G11: South | H11: 3 | I11: 1490 | J11: 0.15 | K11: 3799.5 | L11: 2609.33 | M11: 1190.17 | N11: Debit Card
A12: ORD10078 | B12: 45667 | C12: =DATE(YEAR(B12),MONTH(B12),1) -> 45658 | D12: CUST1329 | E12: Air Fryer | F12: Home & Kitchen | G12: West | H12: 1 | I12: 5320 | J12: 0.15 | K12: 4522 | L12: 3521.99 | M12: 1000.01 | N12: Credit Card
A13: ORD10173 | B13: 45667 | C13: =DATE(YEAR(B13),MONTH(B13),1) -> 45658 | D13: CUST1068 | E13: Wireless Earbuds | F13: Electronics | G13: South | H13: 4 | I13: 2510 | J13: 0.15 | K13: 8534 | L13: 6109.1 | M13: 2424.9 | N13: UPI
... A501: ORD10446 | B501: 46264 | C501: =DATE(YEAR(B501),MONTH(B501),1) -> 46235 | D501: CUST1106 | E501: Smart Watch | F501: Electronics | G501: West | H501: 1 | I501: 4090 | J501: 0.1 | K501: 3681 | L501: 2543.72 | M501: 1137.28 | N501: Credit Card

Sheet Analysis
A1: E-Commerce Business Analytics
A3: Metric | B3: Value
A4: Total Revenue | B4: =SUM(Ecommerce_Data[Sales]) -> 2302554
A5: Total Cost | B5: =SUM(Ecommerce_Data[Cost]) -> 1543854
A6: Total Profit | B6: =SUM(Ecommerce_Data[Profit]) -> 758699.98
A7: Total Orders | B7: =COUNTA(Ecommerce_Data[Order_ID]) -> 500
A8: Total Quatity Sold | B8: =SUM(Ecommerce_Data[Quantity]) -> 980
A9: Average Order Values | B9: =B4/B7 -> 4605.108
A10: Profit Margin | B10: =B6/B4 -> 0.32950366
A11: Unique Customers | B11: =COUNTA(_xlfn.UNIQUE(Ecommerce_Data[Customer_ID])) -> 263

Sheet Category_Analysis
